[{"userProfilePK":106740377,"calendarDate":{"date":"Feb 26, 2022 12:00:00 AM"},"uuid":"660f7cf36ed24809aa3d65b797facbde","durationInMilliseconds":0,"totalKilocalories":366.0,"activeKilocalories":366.0,"burnedKilocalories":366.0,"remainingKilocalories":366.0,"totalDistanceMeters":5000,"includesWellnessData":false,"includesActivityData":true,"includesCalorieConsumedData":false,"allDayStress":{},"version":2,"hydration":{"userProfilePK":106740377,"calendarDate":{"date":"Feb 26, 2022 12:00:00 AM"},"valueInML":0.0,"activityIntakeInML":0.0,"goalInML":2839.056,"capped":false,"sweatLossInML":158.0,"adjustedGoalInML":2997.056,"lastEntryTimestampLocal":{"date":"Feb 26, 2022 3:59:20 PM"}}},{"userProfilePK":106740377,"calendarDate":{"date":"Feb 28, 2022 12:00:00 AM"},"uuid":"f3be44f0af64494390d77a8d272ba4e9","durationInMilliseconds":0,"totalKilocalories":213.0,"activeKilocalories":213.0,"burnedKilocalories":213.0,"remainingKilocalories":213.0,"totalDistanceMeters":2739,"includesWellnessData":false,"includesActivityData":true,"includesCalorieConsumedData":false,"allDayStress":{},"version":2,"hydration":{"userProfilePK":106740377,"calendarDate":{"date":"Feb 28, 2022 12:00:00 AM"},"valueInML":0.0,"activityIntakeInML":0.0,"goalInML":2839.056,"capped":false,"sweatLossInML":103.0,"adjustedGoalInML":2942.056,"lastEntryTimestampLocal":{"date":"Feb 28, 2022 5:49:58 PM"}}},{"userProfilePK":106740377,"calendarDate":{"date":"Mar 2, 2022 12:00:00 AM"},"uuid":"64e9a2adf23a435c92f49b077eecdffd","durationInMilliseconds":0,"totalKilocalories":159.0,"activeKilocalories":159.0,"burnedKilocalories":159.0,"remainingKilocalories":159.0,"totalDistanceMeters":2141,"includesWellnessData":false,"includesActivityData":true,"includesCalorieConsumedData":false,"allDayStress":{},"version":2,"hydration":{"userProfilePK":106740377,"calendarDate":{"date":"Mar 2, 2022 12:00:00 AM"},"valueInML":0.0,"activityIntakeInML":0.0,"goalInML":2839.056,"capped":false,"sweatLossInML":68.0,"adjustedGoalInML":2907.056,"lastEntryTimestampLocal":{"date":"Mar 2, 2022 5:32:05 PM"}}},{"userProfilePK":106740377,"calendarDate":{"date":"Mar 5, 2022 12:00:00 AM"},"uuid":"9b69d93e2a8c4627b63492633061e56f","durationInMilliseconds":0,"totalKilocalories":296.0,"activeKilocalories":296.0,"burnedKilocalories":296.0,"remainingKilocalories":296.0,"totalDistanceMeters":4525,"includesWellnessData":false,"includesActivityData":true,"includesCalorieConsumedData":false,"allDayStress":{},"version":2,"hydration":{"userProfilePK":106740377,"calendarDate":{"date":"Mar 5, 2022 12:00:00 AM"},"valueInML":0.0,"activityIntakeInML":0.0,"goalInML":2839.056,"capped":false,"sweatLossInML":149.0,"adjustedGoalInML":2988.056,"lastEntryTimestampLocal":{"date":"Mar 5, 2022 6:15:52 PM"}}},{"userProfilePK":106740377,"calendarDate":{"date":"Mar 7, 2022 12:00:00 AM"},"uuid":"2a81a150e1f74d8285d6c0055687f587","durationInMilliseconds":0,"totalKilocalories":392.0,"activeKilocalories":392.0,"burnedKilocalories":392.0,"remainingKilocalories":392.0,"totalDistanceMeters":4966,"includesWellnessData":false,"includesActivityData":true,"includesCalorieConsumedData":false,"allDayStress":{},"version":2,"hydration":{"userProfilePK":106740377,"calendarDate":{"date":"Mar 7, 2022 12:00:00 AM"},"valueInML":0.0,"activityIntakeInML":0.0,"goalInML":2839.056,"capped":false,"sweatLossInML":169.0,"adjustedGoalInML":3008.056,"lastEntryTimestampLocal":{"date":"Mar 7, 2022 5:41:01 PM"}}},{"userProfilePK":106740377,"calendarDate":{"date":"Mar 12, 2022 12:00:00 AM"},"uuid":"2ceb618c9d96448c820a0be5b65d30d9","durationInMilliseconds":0,"totalKilocalories":486.0,"activeKilocalories":486.0,"burnedKilocalories":486.0,"remainingKilocalories":486.0,"totalDistanceMeters":5989,"includesWellnessData":false,"includesActivityData":true,"includesCalorieConsumedData":false,"allDayStress":{},"version":2,"hydration":{"userProfilePK":106740377,"calendarDate":{"date":"Mar 12, 2022 12:00:00 AM"},"valueInML":0.0,"activityIntakeInML":0.0,"goalInML":2839.056,"capped":false,"sweatLossInML":195.0,"adjustedGoalInML":3034.056,"lastEntryTimestampLocal":{"date":"Mar 12, 2022 2:25:53 PM"}}},{"userProfilePK":106740377,"calendarDate":{"date":"Mar 19, 2022 12:00:00 AM"},"uuid":"0153ecffbf94429b989cbfdeda3d605c","durationInMilliseconds":0,"totalKilocalories":196.0,"activeKilocalories":196.0,"burnedKilocalories":196.0,"remainingKilocalories":196.0,"totalDistanceMeters":3740,"includesWellnessData":false,"includesActivityData":true,"includesCalorieConsumedData":false,"allDayStress":{},"version":2,"hydration":{"userProfilePK":106740377,"calendarDate":{"date":"Mar 19, 2022 12:00:00 AM"},"valueInML":0.0,"activityIntakeInML":0.0,"goalInML":2839.056,"capped":false,"sweatLossInML":114.0,"adjustedGoalInML":2953.056,"lastEntryTimestampLocal":{"date":"Mar 19, 2022 5:28:35 PM"}}},{"userProfilePK":106740377,"calendarDate":{"date":"Mar 24, 2022 12:00:00 AM"},"uuid":"63271fb7cfe749f8a4eb3ce21bb6651d","durationInMilliseconds":0,"totalKilocalories":312.0,"activeKilocalories":312.0,"burnedKilocalories":312.0,"remainingKilocalories":312.0,"totalDistanceMeters":4623,"includesWellnessData":false,"includesActivityData":true,"includesCalorieConsumedData":false,"allDayStress":{},"version":2,"hydration":{"userProfilePK":106740377,"calendarDate":{"date":"Mar 24, 2022 12:00:00 AM"},"valueInML":0.0,"activityIntakeInML":0.0,"goalInML":2839.056,"capped":false,"sweatLossInML":138.0,"adjustedGoalInML":2977.056,"lastEntryTimestampLocal":{"date":"Mar 24, 2022 5:28:51 PM"}}},{"userProfilePK":106740377,"calendarDate":{"date":"Apr 4, 2022 12:00:00 AM"},"uuid":"d2a6ef3b38f5489ebcaebf5d9e989cfe","durationInMilliseconds":0,"totalKilocalories":223.0,"activeKilocalories":223.0,"burnedKilocalories":223.0,"remainingKilocalories":223.0,"totalDistanceMeters":2867,"includesWellnessData":false,"includesActivityData":true,"includesCalorieConsumedData":false,"allDayStress":{},"version":2,"hydration":{"userProfilePK":106740377,"calendarDate":{"date":"Apr 4, 2022 12:00:00 AM"},"valueInML":0.0,"activityIntakeInML":0.0,"goalInML":2839.056,"capped":false,"sweatLossInML":111.0,"adjustedGoalInML":2950.056,"lastEntryTimestampLocal":{"date":"Apr 4, 2022 5:49:25 PM"}}},{"userProfilePK":106740377,"calendarDate":{"date":"Apr 9, 2022 12:00:00 AM"},"uuid":"b0e0a3c8b18344bd88593798aecf8e2a","durationInMilliseconds":0,"totalKilocalories":85.0,"activeKilocalories":85.0,"burnedKilocalories":85.0,"remainingKilocalories":85.0,"totalDistanceMeters":920,"includesWellnessData":false,"includesActivityData":true,"includesCalorieConsumedData":false,"allDayStress":{},"version":2,"hydration":{"userProfilePK":106740377,"calendarDate":{"date":"Apr 9, 2022 12:00:00 AM"},"valueInML":0.0,"activityIntakeInML":0.0,"goalInML":2839.056,"capped":false,"sweatLossInML":41.0,"adjustedGoalInML":2880.056,"lastEntryTimestampLocal":{"date":"Apr 9, 2022 6:36:52 PM"}}},{"userProfilePK":106740377,"calendarDate":{"date":"Apr 10, 2022 12:00:00 AM"},"uuid":"bd4c0d7e94d74408b4f9b49d1cda3d32","durationInMilliseconds":0,"totalKilocalories":159.0,"activeKilocalories":159.0,"burnedKilocalories":159.0,"remainingKilocalories":159.0,"totalDistanceMeters":1869,"includesWellnessData":false,"includesActivityData":true,"includesCalorieConsumedData":false,"allDayStress":{},"version":2,"hydration":{"userProfilePK":106740377,"calendarDate":{"date":"Apr 10, 2022 12:00:00 AM"},"valueInML":0.0,"activityIntakeInML":0.0,"goalInML":2839.056,"capped":false,"sweatLossInML":63.0,"adjustedGoalInML":2902.056,"lastEntryTimestampLocal":{"date":"Apr 10, 2022 12:06:19 PM"}}},{"userProfilePK":106740377,"calendarDate":{"date":"Apr 25, 2022 12:00:00 AM"},"uuid":"cbd5f05a05864244bc03c4758d65bf1c","durationInMilliseconds":0,"totalKilocalories":164.0,"activeKilocalories":164.0,"burnedKilocalories":164.0,"remainingKilocalories":164.0,"totalDistanceMeters":2183,"includesWellnessData":false,"includesActivityData":true,"includesCalorieConsumedData":false,"allDayStress":{},"version":2,"hydration":{"userProfilePK":106740377,"calendarDate":{"date":"Apr 25, 2022 12:00:00 AM"},"valueInML":0.0,"activityIntakeInML":0.0,"goalInML":2839.056,"capped":false,"sweatLossInML":75.0,"adjustedGoalInML":2914.056,"lastEntryTimestampLocal":{"date":"Apr 25, 2022 6:01:08 PM"}}},{"userProfilePK":106740377,"calendarDate":{"date":"May 1, 2022 12:00:00 AM"},"uuid":"15a61f9e369f4853ae6efaa1f6a59eb0","durationInMilliseconds":0,"totalKilocalories":485.0,"activeKilocalories":485.0,"burnedKilocalories":485.0,"remainingKilocalories":485.0,"totalDistanceMeters":5602,"includesWellnessData":false,"includesActivityData":true,"includesCalorieConsumedData":false,"allDayStress":{},"version":2,"hydration":{"userProfilePK":106740377,"calendarDate":{"date":"May 1, 2022 12:00:00 AM"},"valueInML":0.0,"activityIntakeInML":0.0,"goalInML":2839.056,"capped":false,"sweatLossInML":190.0,"adjustedGoalInML":3029.056,"lastEntryTimestampLocal":{"date":"May 1, 2022 5:16:14 PM"}}},{"userProfilePK":106740377,"calendarDate":{"date":"May 8, 2022 12:00:00 AM"},"uuid":"dc2d85482f3f4b29b875dcbcc01e02eb","durationInMilliseconds":0,"totalKilocalories":470.0,"activeKilocalories":470.0,"burnedKilocalories":470.0,"remainingKilocalories":470.0,"totalDistanceMeters":5307,"includesWellnessData":false,"includesActivityData":true,"includesCalorieConsumedData":false,"allDayStress":{},"version":2,"hydration":{"userProfilePK":106740377,"calendarDate":{"date":"May 8, 2022 12:00:00 AM"},"valueInML":0.0,"activityIntakeInML":0.0,"goalInML":2839.056,"capped":false,"sweatLossInML":179.0,"adjustedGoalInML":3018.056,"lastEntryTimestampLocal":{"date":"May 8, 2022 1:40:44 PM"}}},{"userProfilePK":106740377,"calendarDate":{"date":"May 31, 2022 12:00:00 AM"},"uuid":"c429cdb48cc64e168dd60ab172c05e12","durationInMilliseconds":0,"totalKilocalories":480.0,"activeKilocalories":480.0,"burnedKilocalories":480.0,"remainingKilocalories":480.0,"totalDistanceMeters":5814,"includesWellnessData":false,"includesActivityData":true,"includesCalorieConsumedData":false,"allDayStress":{},"version":2,"hydration":{"userProfilePK":106740377,"calendarDate":{"date":"May 31, 2022 12:00:00 AM"},"valueInML":0.0,"activityIntakeInML":0.0,"goalInML":2839.056,"capped":false,"sweatLossInML":188.0,"adjustedGoalInML":3027.056,"lastEntryTimestampLocal":{"date":"May 31, 2022 3:29:14 PM"}}}]